mycalclib/__init__.py
mycalclib/myfunctions.py
mycalclib-0.1.0.dist-info/METADATA
mycalclib-0.1.0.dist-info/WHEEL
mycalclib-0.1.0.dist-info/top_level.txt
mycalclib-0.1.0.dist-info/RECORD
